multisim/__init__.py
multisim/simulator.py
multisim_neuro-0.1.dist-info/licenses/LICENSE
multisim_neuro-0.1.dist-info/METADATA
multisim_neuro-0.1.dist-info/WHEEL
multisim_neuro-0.1.dist-info/top_level.txt
multisim_neuro-0.1.dist-info/RECORD
