Metadata-Version: 2.4
Name: multisim-neuro
Version: 0.1
Summary: A package for simulating time resolved data with multivariate effects
Author-email: Alex Lepauvre <alex.lepauvre@gmail.com>
License: MIT License
Project-URL: Homepage, https://github.com/AlexLepauvre/multisim-neuro
Project-URL: Repository, https://github.com/AlexLepauvre/multisim-neuro
License-File: LICENSE
Requires-Dist: numpy
Requires-Dist: pandas
Provides-Extra: docs
Requires-Dist: mne; extra == "docs"
Requires-Dist: eeglabio; extra == "docs"
Requires-Dist: scikit-learn; extra == "docs"
Requires-Dist: scipy; extra == "docs"
Requires-Dist: pydata-sphinx-theme; extra == "docs"
Requires-Dist: numpydoc; extra == "docs"
Requires-Dist: nbsphinx; extra == "docs"
Requires-Dist: ruff; extra == "docs"
Requires-Dist: ipython; extra == "docs"
Requires-Dist: sphinxcontrib-bibtex; extra == "docs"
Requires-Dist: myst-nb; extra == "docs"
Provides-Extra: export
Requires-Dist: mne; extra == "export"
Requires-Dist: eeglabio; extra == "export"
Provides-Extra: dev
Requires-Dist: pytest; extra == "dev"
Dynamic: license-file
